setup.py
janus_py.egg-info/PKG-INFO
janus_py.egg-info/SOURCES.txt
janus_py.egg-info/dependency_links.txt
janus_py.egg-info/entry_points.txt
janus_py.egg-info/requires.txt
janus_py.egg-info/top_level.txt
sr/__init__.py
sr/sr.py