Metadata-Version: 1.1
Name: janus-py
Version: 0.1
Summary: Python interface to the Janus SSP REST API (see https://github.com/janus-ssp/janus)
Home-page: https://github.com/baszoetekouw/janus-py
Author: Bas Zoetekouw
Author-email: bas.zoetekouw@surfnet.nl
License: APL2
Keywords: janus api interface
Platform: UNKNOWN
Classifier: Development Status :: 3 - Alpha
Classifier: Intended Audience :: Developers
Classifier: License :: DFSG approved
Classifier: License :: OSI Approved :: Apache Software License
Classifier: Programming Language :: Python :: 3
